winpaths/__init__.py
bp_winpaths-0.2.dist-info/METADATA
bp_winpaths-0.2.dist-info/WHEEL
bp_winpaths-0.2.dist-info/top_level.txt
bp_winpaths-0.2.dist-info/RECORD
