Metadata-Version: 2.1
Name: bp-winpaths
Version: 0.2
Summary: Retrieves common Windows system paths as Unicode strings.
Home-page: https://github.com/blindpandas/bp-winpaths
Author: Blind Pandas Team (original: Ryan Ginstrom)
Author-email: info@blindpandas.com
License: MIT
Keywords: os path system
Platform: UNKNOWN
Classifier: Development Status :: 4 - Beta
Classifier: Intended Audience :: Developers
Classifier: Operating System :: OS Independent
Classifier: License :: OSI Approved :: MIT License
Classifier: Topic :: Software Development :: Libraries
Classifier: Natural Language :: English
Classifier: Programming Language :: Python :: 3
